{
  "amber": 49189,
  "animalic": 17560,
  "aromatic": 56403,
  "balsamic": 19178,
  "cacao": 2189,
  "caramel": 4252,
  "chocolate": 1677,
  "cinnamon": 4927,
  "citrus": 61866,
  "earthy": 22697,
  "floral": 48565,
  "fresh": 35343,
  "fresh spicy": 49308,
  "fruity": 45028,
  "green": 30212,
  "honey": 3685,
  "lavender": 9477,
  "leather": 11960,
  "metallic": 2789,
  "musky": 45680,
  "nutty": 3878,
  "patchouli": 18050,
  "powdery": 66564,
  "rose": 27539,
  "soft spicy": 13767,
  "sweet": 62858,
  "tobacco": 4931,
  "vanilla": 37543,
  "violet": 9056,
  "warm spicy": 49031,
  "white floral": 42228,
  "woody": 83698
}